setup.py
googlesheets/__init__.py
googlesheets/connection.py
googlesheets/sheet.py
googlesheets/spreadsheet.py
googlesheets/util.py
googlesheets.egg-info/PKG-INFO
googlesheets.egg-info/SOURCES.txt
googlesheets.egg-info/dependency_links.txt
googlesheets.egg-info/namespace_packages.txt
googlesheets.egg-info/not-zip-safe
googlesheets.egg-info/requires.txt
googlesheets.egg-info/top_level.txt