Metadata-Version: 1.1
Name: googlesheets
Version: 0.1
Summary: Simply read and write Google Spreadsheets from Python
Home-page: http://github.com/pudo/googlesheets
Author: Friedrich Lindenberg
Author-email: friedrich@pudo.org
License: MIT
Keywords: sheet spreadsheets tables
Platform: UNKNOWN
Classifier: Development Status :: 3 - Alpha
Classifier: Intended Audience :: Developers
Classifier: License :: OSI Approved :: MIT License
Classifier: Operating System :: OS Independent
Classifier: Programming Language :: Python :: 2.6
Classifier: Programming Language :: Python :: 2.7
Classifier: Programming Language :: Python :: 3.3
